polarimetry/PyPOLAR.py
polarimetry/generate_json.py
polarimetry/pypolar_classes.py
polarimetry/calibration/Calib_20231009_2D.txt
polarimetry/calibration/Calib_th_2D.txt
polarimetry/calibration/Calib_th_3D.txt
polarimetry/diskcones/Disk_Ga-0.1_Pa10_Ta0_Gb0.1_Pb30_Tb0_Gc0.2_Pc0_Tc0.mat
polarimetry/diskcones/Disk_Ga-0.1_Pa20_Ta0_Gb-0.1_Pb10_Tb45_Gc-0.2_Pc0_Tc0.mat
polarimetry/diskcones/Disk_Ga-0.1_Pa20_Ta0_Gb-0.1_Pb10_Tb45_Gc0.1_Pc0_Tc0.mat
polarimetry/diskcones/Disk_Ga-0.1_Pa20_Ta0_Gb-0.1_Pb20_Tb45_Gc-0.2_Pc0_Tc0.mat
polarimetry/diskcones/Disk_Ga-0.2_Pa0_Ta0_Gb0.1_Pb0_Tb0_Gc-0.2_Pc0_Tc0.mat
polarimetry/diskcones/Disk_Ga-0.2_Pa0_Ta0_Gb0.2_Pb20_Tb0_Gc-0.2_Pc0_Tc0.mat
polarimetry/diskcones/Disk_Ga-0.2_Pa0_Ta45_Gb0.1_Pb0_Tb45_Gc-0.1_Pc0_Tc0.mat
polarimetry/diskcones/Disk_Ga0.1_Pa0_Ta45_Gb-0.1_Pb20_Tb0_Gc-0.1_Pc0_Tc0.mat
polarimetry/diskcones/Disk_Ga0_Pa0_Ta0_Gb0_Pb0_Tb0_Gc0_Pc0_Tc0.mat
polarimetry/diskcones/Disk_Ga0_Pa20_Ta45_Gb-0.1_Pb0_Tb0_Gc-0.1_Pc0_Tc0.mat
polarimetry/icons/GitHub.png
polarimetry/icons/backward.png
polarimetry/icons/blur_circular-512.png
polarimetry/icons/blur_circular.png
polarimetry/icons/build.png
polarimetry/icons/build_fill.png
polarimetry/icons/check_circle.png
polarimetry/icons/clockwise.png
polarimetry/icons/close.png
polarimetry/icons/colorize.png
polarimetry/icons/construction.png
polarimetry/icons/contact_support.png
polarimetry/icons/contrast.png
polarimetry/icons/counterclockwise.png
polarimetry/icons/crop.png
polarimetry/icons/delete.png
polarimetry/icons/delete_forever.png
polarimetry/icons/download.png
polarimetry/icons/download_file.png
polarimetry/icons/download_folder.png
polarimetry/icons/folder_open.png
polarimetry/icons/format_list.png
polarimetry/icons/forward.png
polarimetry/icons/home.png
polarimetry/icons/imagesmode.png
polarimetry/icons/layers_clear.png
polarimetry/icons/mail.png
polarimetry/icons/merge.png
polarimetry/icons/microscope.png
polarimetry/icons/multiline_chart.png
polarimetry/icons/open_in_new.png
polarimetry-2.9.0.dist-info/licenses/LICENSE
polarimetry-2.9.0.dist-info/METADATA
polarimetry-2.9.0.dist-info/WHEEL
polarimetry-2.9.0.dist-info/entry_points.txt
polarimetry-2.9.0.dist-info/top_level.txt
polarimetry-2.9.0.dist-info/RECORD
