Metadata-Version: 2.4
Name: Polarimetry
Version: 2.9.0
Summary: PyPOLAR is a Python-based app for analyzing polarization-resolved microscopy data to measure molecular orientation and order in biological samples
Author-email: Cristel Chandre <cristel.chandre@cnrs.fr>, Manos Mavrakis <manos.mavrakis@fresnel.fr>, Sophie Brasselet <sophie.brasselet@fresnel.fr>
Maintainer-email: Cristel Chandre <cristel.chandre@cnrs.fr>
License: BSD 2-Clause License
Project-URL: Homepage, https://www.fresnel.fr/polarimetry
Project-URL: GitHub, https://github.com/cchandre/Polarimetry
Project-URL: Wiki, https://github.com/cchandre/Polarimetry/wiki
Keywords: polarimetry,microscopy,molecular orientation
Classifier: Programming Language :: Python :: 3
Classifier: Intended Audience :: Education
Classifier: Intended Audience :: Science/Research
Classifier: Operating System :: OS Independent
Classifier: Topic :: Scientific/Engineering
Classifier: Topic :: Scientific/Engineering :: Visualization
Classifier: Topic :: Scientific/Engineering :: Image Processing
Classifier: Topic :: Scientific/Engineering :: Physics
Classifier: Topic :: Scientific/Engineering :: Medical Science Apps.
Requires-Python: >=3.8
License-File: LICENSE
Requires-Dist: colorcet==3.0.1
Requires-Dist: customtkinter==5.2.0
Requires-Dist: joblib==1.2.0
Requires-Dist: matplotlib==3.6.2
Requires-Dist: numpy==1.23.5
Requires-Dist: opencv-python==4.8.1.78
Requires-Dist: openpyxl==3.0.9
Requires-Dist: pillow==10.3.0
Requires-Dist: scikit-image==0.20.0
Requires-Dist: scipy==1.9.1
Requires-Dist: tksheet==6.2.5
Requires-Dist: tifffile==2024.12.12
Requires-Dist: roifile==2023.5.12
Dynamic: license-file
